<annotation>
	<folder>train</folder>
	<filename>im278.jpg</filename>
	<path>/home/younes/vision/train/im278.jpg</path>
	<source>
		<database>Unknown</database>
	</source>
	<size>
		<width>800</width>
		<height>533</height>
		<depth>3</depth>
	</size>
	<segmented>0</segmented>
	<object>
		<name>t72</name>
		<pose>Unspecified</pose>
		<truncated>0</truncated>
		<difficult>0</difficult>
		<bndbox>
			<xmin>84</xmin>
			<ymin>206</ymin>
			<xmax>559</xmax>
			<ymax>387</ymax>
		</bndbox>
	</object>
</annotation>
